vpype_embroidery/efill.py
vpype_embroidery/eread.py
vpype_embroidery/ewrite.py
vpype_embroidery-0.3.2.dist-info/LICENSE
vpype_embroidery-0.3.2.dist-info/METADATA
vpype_embroidery-0.3.2.dist-info/WHEEL
vpype_embroidery-0.3.2.dist-info/entry_points.txt
vpype_embroidery-0.3.2.dist-info/top_level.txt
vpype_embroidery-0.3.2.dist-info/RECORD
