Metadata-Version: 2.1
Name: vpype-embroidery
Version: 0.3.2
Summary: vpype embroidery plugin
Home-page: https://github.com/embroidepy/vpype-embroidery/
Author: Tatarize
Author-email: tatarize@gmail.com
Classifier: Programming Language :: Python :: 3.7
Classifier: Programming Language :: Python :: 3.8
Classifier: Programming Language :: Python :: 3.9
Classifier: Programming Language :: Python :: 3.10
Classifier: Programming Language :: Python :: 3.11
Classifier: Programming Language :: Python :: 3.12
Classifier: License :: OSI Approved :: MIT License
Classifier: Operating System :: OS Independent
License-File: LICENSE
Requires-Dist: click
Requires-Dist: vpype <2.0,>=1.9
Requires-Dist: numpy
Requires-Dist: pyembroidery >=1.5.0
